RenderPy/CSG.py
RenderPy/Camera.py
RenderPy/Canvas.py
RenderPy/Color.py
RenderPy/Computation.py
RenderPy/Cone.py
RenderPy/Cube.py
RenderPy/Cylinder.py
RenderPy/Group.py
RenderPy/Intersection.py
RenderPy/Light.py
RenderPy/Material.py
RenderPy/Matrix.py
RenderPy/ObjParser.py
RenderPy/Pattern.py
RenderPy/Plane.py
RenderPy/Ray.py
RenderPy/Shape.py
RenderPy/Sphere.py
RenderPy/Triangle.py
RenderPy/Tuple.py
RenderPy/World.py
RenderPy/__init__.py
3dRenderPy-0.0.5.dist-info/LICENSE
3dRenderPy-0.0.5.dist-info/METADATA
3dRenderPy-0.0.5.dist-info/WHEEL
3dRenderPy-0.0.5.dist-info/top_level.txt
3dRenderPy-0.0.5.dist-info/RECORD
