Metadata-Version: 2.1
Name: 3dRenderPy
Version: 0.0.5
Summary: This is an implementation of a ray tracer based on Jamis Buck's The Ray Tracer Challenge. It supports several primitives.
Home-page: https://github.com/woes-lynne/3DRenderPy
Author: Ulysses Lynne
Author-email: yufeilin@bennington.edu
License: UNKNOWN
Project-URL: Bug Tracker, https://github.com/woes-lynne/3DRenderPy/issues
Platform: UNKNOWN
Classifier: Programming Language :: Python :: 3
Classifier: License :: OSI Approved :: MIT License
Classifier: Operating System :: OS Independent
Requires-Python: >=3.6
License-File: LICENSE
Requires-Dist: numpy (>=1.19.5)
Requires-Dist: Pillow (>=5.1.0)
